tools/__init__.py
tools/core.py
bwfilter_python-0.1.0.dist-info/LICENSE
bwfilter_python-0.1.0.dist-info/METADATA
bwfilter_python-0.1.0.dist-info/WHEEL
bwfilter_python-0.1.0.dist-info/top_level.txt
bwfilter_python-0.1.0.dist-info/RECORD
