Metadata-Version: 2.1
Name: bwfilter-python
Version: 0.1.0
Summary: Pacote simples para edição de imagens
Home-page: https://github.com/giuliagranado/bwfilter-python
Author: Giulia Granado
Classifier: Programming Language :: Python :: 3
Classifier: License :: OSI Approved :: MIT License
License-File: LICENSE
Requires-Dist: Pillow
